Metadata-Version: 2.1
Name: ringcentral-bot-framework-extension-botinfo
Version: 0.4.0
Summary: Simple ringcentral chatbot framework python extension that add `bot info` command support.
Home-page: https://github.com/zxdong262/ringcentral-chatbot-python-ext-bot-info
Author: Drake Zhao
Author-email: drake.zhao@ringcentral.com
License: UNKNOWN
Keywords: ringcentral,bot,framework
Platform: UNKNOWN
Classifier: Programming Language :: Python :: 3
Classifier: License :: OSI Approved :: MIT License
Classifier: Operating System :: OS Independent
